{"Col-0":{"rep_02":"train","rep_04":"test","rep_07":"train","rep_10":"train","rep_13":"valid","rep_14":"valid","rep_15":"train","rep_16":"train","rep_18":"test","rep_19":"test","rep_20":"test","rep_21":"test","rep_22":"train","rep_24":"train","rep_30":"train","rep_32":"test","rep_33":"train","rep_34":"train","rep_35":"train","rep_36":"train","rep_38":"valid","rep_40":"train","rep_41":"train","rep_42":"train","rep_43":"train","rep_44":"train","rep_45":"train","rep_46":"train","rep_47":"train","rep_48":"train"},"Cvi-0":{"rep_01":"valid","rep_02":"train","rep_03":"train","rep_05":"train","rep_06":"valid","rep_08":"train","rep_09":"valid","rep_10":"test","rep_11":"test","rep_12":"train","rep_14":"train","rep_16":"test","rep_17":"train","rep_18":"train","rep_19":"test","rep_20":"train","rep_21":"test","rep_22":"train","rep_23":"train","rep_25":"train","rep_26":"train","rep_29":"train","rep_30":"train","rep_31":"train","rep_32":"test","rep_35":"test","rep_37":"train","rep_39":"train","rep_40":"train","rep_41":"train","rep_42":"train","rep_43":"train","rep_44":"train","rep_45":"train","rep_46":"train"},"Is-1":{"rep_01":"test","rep_02":"train","rep_03":"valid","rep_04":"train","rep_05":"train","rep_08":"train","rep_09":"train","rep_10":"train","rep_11":"train","rep_12":"train","rep_13":"test","rep_14":"valid","rep_15":"train","rep_16":"train","rep_17":"train","rep_18":"test","rep_19":"train","rep_22":"test","rep_23":"test","rep_24":"train","rep_28":"train","rep_32":"train","rep_34":"test","rep_38":"train","rep_40":"valid","rep_41":"train","rep_42":"train","rep_43":"train","rep_44":"train","rep_45":"train","rep_46":"train","rep_47":"train"},"Kz-9":{"rep_01":"test","rep_02":"train","rep_04":"train","rep_05":"train","rep_06":"test","rep_07":"train","rep_08":"test","rep_09":"train","rep_10":"test","rep_12":"valid","rep_14":"train","rep_15":"train","rep_16":"train","rep_19":"train","rep_20":"test","rep_21":"train","rep_23":"test","rep_24":"train","rep_25":"train","rep_26":"test","rep_27":"train","rep_29":"train","rep_30":"train","rep_31":"train","rep_32":"train","rep_33":"train","rep_36":"train","rep_37":"valid","rep_38":"valid","rep_39":"train","rep_40":"train","rep_41":"train","rep_42":"train","rep_43":"train","rep_44":"train","rep_45":"train","rep_46":"train","rep_47":"train","rep_48":"train"},"Ler-1":{"rep_03":"test","rep_04":"train","rep_07":"train","rep_11":"train","rep_13":"train","rep_15":"train","rep_16":"valid","rep_17":"train","rep_18":"valid","rep_19":"test","rep_20":"train","rep_23":"test","rep_24":"test","rep_26":"train","rep_28":"train","rep_29":"train","rep_31":"train","rep_35":"train","rep_36":"train","rep_37":"train","rep_39":"train","rep_40":"test","rep_41":"train","rep_42":"train","rep_43":"train","rep_44":"train","rep_45":"train","rep_46":"train","rep_47":"train"},"TOU-I-17":{"rep_03":"train","rep_04":"train","rep_05":"train","rep_06":"train","rep_07":"train","rep_11":"train","rep_13":"valid","rep_15":"test","rep_18":"test","rep_19":"train","rep_21":"train","rep_22":"test","rep_23":"train","rep_25":"train","rep_26":"valid","rep_27":"train","rep_30":"test","rep_31":"test","rep_32":"train","rep_33":"test","rep_34":"train","rep_35":"valid","rep_36":"train","rep_37":"train","rep_38":"train","rep_40":"train","rep_41":"train","rep_42":"train","rep_43":"train","rep_44":"train","rep_45":"train","rep_46":"train","rep_47":"train","rep_48":"train"},"Uk-1":{"rep_03":"valid","rep_06":"train","rep_09":"train","rep_12":"train","rep_13":"train","rep_14":"test","rep_18":"test","rep_19":"train","rep_23":"train","rep_25":"test","rep_28":"train","rep_30":"train","rep_31":"train","rep_32":"train","rep_34":"train","rep_35":"train","rep_36":"test","rep_37":"valid","rep_38":"train","rep_39":"train","rep_40":"train","rep_41":"train","rep_42":"train","rep_43":"test","rep_44":"train","rep_45":"train"},"Zdr-1":{"rep_02":"test","rep_05":"train","rep_08":"valid","rep_12":"valid","rep_15":"train","rep_17":"train","rep_18":"train","rep_19":"test","rep_20":"train","rep_24":"train","rep_25":"train","rep_26":"train","rep_27":"test","rep_29":"test","rep_31":"train","rep_34":"test","rep_36":"train","rep_37":"train","rep_38":"train","rep_40":"train","rep_41":"train","rep_42":"train","rep_43":"train","rep_44":"train","rep_45":"train","rep_47":"train","rep_48":"train","rep_49":"train"}}
